{
    "type": "bundle",
    "id": "bundle--4924560a-e70e-4516-92e3-ad196c8ffe99",
    "objects": [
        {
            "type": "identity",
            "spec_version": "2.1",
            "id": "identity--0581a0ae-0be3-473a-a9fe-eb784433f1fa",
            "created": "2025-09-03T16:02:49.416936Z",
            "modified": "2025-09-03T16:02:49.416936Z",
            "name": "NCSC",
            "description": "The UK National Cyber Security Centre (NCSC) is the primary author and publisher of this report, providing technical analysis, detection guidance, and YARA rules for identifying Smooth Operator malware.",
            "identity_class": "organization"
        },
        {
            "type": "marking-definition",
            "spec_version": "2.1",
            "id": "marking-definition--613f2e26-407d-48c7-9eca-b8e91df99dc9",
            "created": "2017-01-20T00:00:00.000Z",
            "definition_type": "tlp",
            "name": "TLP:WHITE",
            "definition": {
                "tlp": "white"
            }
        },
        {
            "type": "url",
            "spec_version": "2.1",
            "id": "url--3ca77848-3c86-5177-b9c7-262d440d813f",
            "value": "https://msstorageazure.com/analysis"
        },
        {
            "type": "url",
            "spec_version": "2.1",
            "id": "url--3ce4a838-3d16-5dae-a0e0-e04cd86b5de5",
            "value": "https://officestoragebox.com/api/biosync"
        },
        {
            "type": "url",
            "spec_version": "2.1",
            "id": "url--c0df7321-5a23-5833-a830-d26ac9be888a",
            "value": "https://visualstudiofactory.com/groupcore"
        },
        {
            "type": "url",
            "spec_version": "2.1",
            "id": "url--9bb50a9b-3b49-5ec4-bd4b-f6218f0a3291",
            "value": "https://azuredeploystore.com/cloud/images"
        },
        {
            "type": "url",
            "spec_version": "2.1",
            "id": "url--dbe40f12-c563-5543-859e-b7e68f643b2e",
            "value": "https://msstorageboxes.com/xbox"
        },
        {
            "type": "url",
            "spec_version": "2.1",
            "id": "url--7fdbe136-4ff2-52f3-a597-f76d4438fdfd",
            "value": "https://officeaddons.com/quality"
        },
        {
            "type": "url",
            "spec_version": "2.1",
            "id": "url--67d95451-80b8-5473-bb76-d2120307ba1b",
            "value": "https://sourceslabs.com/status"
        },
        {
            "type": "url",
            "spec_version": "2.1",
            "id": "url--e6657594-2903-51f3-87db-e23c6b55deef",
            "value": "https://zacharryblogs.com/xmlquery"
        },
        {
            "type": "url",
            "spec_version": "2.1",
            "id": "url--3ea4b73b-cfa2-58dc-9dc7-1cff719316d6",
            "value": "https://pbxcloudeservices.com/network"
        },
        {
            "type": "url",
            "spec_version": "2.1",
            "id": "url--8096d021-fbde-5c5c-bdde-579339fed002",
            "value": "https://pbxphonenetwork.com/phone"
        },
        {
            "type": "url",
            "spec_version": "2.1",
            "id": "url--d4c0c66e-acd2-52b3-b82b-eeb29120e0c6",
            "value": "https://akamaitechcloudservices.com/v2/fileapi"
        },
        {
            "type": "url",
            "spec_version": "2.1",
            "id": "url--62529b3b-96ed-53cf-938e-ae44eca99914",
            "value": "https://azureonlinestorage.com/google/storage"
        },
        {
            "type": "url",
            "spec_version": "2.1",
            "id": "url--6d15f2ac-747b-5b8c-8325-f9994aaf02ee",
            "value": "https://msedgepackageinfo.com/ms-webview"
        },
        {
            "type": "url",
            "spec_version": "2.1",
            "id": "url--230a9427-bc2b-56b1-96a0-5d6274096e11",
            "value": "https://glcloudservice.com/v1/status"
        },
        {
            "type": "url",
            "spec_version": "2.1",
            "id": "url--4523eebd-2121-542b-9aef-3fdaf7184a3f",
            "value": "https://pbxsources.com/queue"
        },
        {
            "type": "url",
            "spec_version": "2.1",
            "id": "url--a91f7562-d8f2-5f71-b267-2be460045132",
            "value": "https://sbmsa.wiki/blog/_insert"
        },
        {
            "type": "indicator",
            "spec_version": "2.1",
            "id": "indicator--34d4da07-0522-4e8a-99e9-960a0b332111",
            "created": "2025-09-03T16:01:21.951975Z",
            "modified": "2025-09-03T16:01:21.951975Z",
            "name": "C2 URL",
            "description": "Smooth Operator C2 server used for command and control.",
            "pattern": "[url:value = 'https://msstorageazure.com/analysis']",
            "pattern_type": "stix",
            "pattern_version": "2.1",
            "valid_from": "2025-09-03T16:01:21.95196Z"
        },
        {
            "type": "indicator",
            "spec_version": "2.1",
            "id": "indicator--a3406e06-71ce-4cac-b448-093cf9067923",
            "created": "2025-09-03T16:01:21.953836Z",
            "modified": "2025-09-03T16:01:21.953836Z",
            "name": "C2 URL",
            "description": "Smooth Operator C2 server used for command and control.",
            "pattern": "[url:value = 'https://officestoragebox.com/api/biosync']",
            "pattern_type": "stix",
            "pattern_version": "2.1",
            "valid_from": "2025-09-03T16:01:21.953824Z"
        },
        {
            "type": "indicator",
            "spec_version": "2.1",
            "id": "indicator--283ce6c3-0eb9-4277-8b1a-a8de401eef30",
            "created": "2025-09-03T16:01:21.955499Z",
            "modified": "2025-09-03T16:01:21.955499Z",
            "name": "C2 URL",
            "description": "Smooth Operator C2 server used for command and control.",
            "pattern": "[url:value = 'https://visualstudiofactory.com/groupcore']",
            "pattern_type": "stix",
            "pattern_version": "2.1",
            "valid_from": "2025-09-03T16:01:21.955491Z"
        },
        {
            "type": "indicator",
            "spec_version": "2.1",
            "id": "indicator--b73e98d7-bee5-4404-8eb1-4b876bab4588",
            "created": "2025-09-03T16:01:21.957101Z",
            "modified": "2025-09-03T16:01:21.957101Z",
            "name": "C2 URL",
            "description": "Smooth Operator C2 server used for command and control.",
            "pattern": "[url:value = 'https://azuredeploystore.com/cloud/images']",
            "pattern_type": "stix",
            "pattern_version": "2.1",
            "valid_from": "2025-09-03T16:01:21.957093Z"
        },
        {
            "type": "indicator",
            "spec_version": "2.1",
            "id": "indicator--bf86823d-fd0f-4c75-9ac4-f4177af58ea8",
            "created": "2025-09-03T16:01:21.958644Z",
            "modified": "2025-09-03T16:01:21.958644Z",
            "name": "C2 URL",
            "description": "Smooth Operator C2 server used for command and control.",
            "pattern": "[url:value = 'https://msstorageboxes.com/xbox']",
            "pattern_type": "stix",
            "pattern_version": "2.1",
            "valid_from": "2025-09-03T16:01:21.958634Z"
        },
        {
            "type": "indicator",
            "spec_version": "2.1",
            "id": "indicator--48f74225-c480-4404-b8c0-118de8de833c",
            "created": "2025-09-03T16:01:21.960181Z",
            "modified": "2025-09-03T16:01:21.960181Z",
            "name": "C2 URL",
            "description": "Smooth Operator C2 server used for command and control.",
            "pattern": "[url:value = 'https://officeaddons.com/quality']",
            "pattern_type": "stix",
            "pattern_version": "2.1",
            "valid_from": "2025-09-03T16:01:21.960173Z"
        },
        {
            "type": "indicator",
            "spec_version": "2.1",
            "id": "indicator--5acc1604-8dc7-4596-aeb5-f750ff08e7d8",
            "created": "2025-09-03T16:01:21.961732Z",
            "modified": "2025-09-03T16:01:21.961732Z",
            "name": "C2 URL",
            "description": "Smooth Operator C2 server used for command and control.",
            "pattern": "[url:value = 'https://sourceslabs.com/status']",
            "pattern_type": "stix",
            "pattern_version": "2.1",
            "valid_from": "2025-09-03T16:01:21.961724Z"
        },
        {
            "type": "indicator",
            "spec_version": "2.1",
            "id": "indicator--3241cd79-ce7b-4846-bc5d-d76743b08873",
            "created": "2025-09-03T16:01:21.963544Z",
            "modified": "2025-09-03T16:01:21.963544Z",
            "name": "C2 URL",
            "description": "Smooth Operator C2 server used for command and control.",
            "pattern": "[url:value = 'https://zacharryblogs.com/xmlquery']",
            "pattern_type": "stix",
            "pattern_version": "2.1",
            "valid_from": "2025-09-03T16:01:21.963537Z"
        },
        {
            "type": "indicator",
            "spec_version": "2.1",
            "id": "indicator--2bb3af37-3765-4530-84aa-db9924b5944c",
            "created": "2025-09-03T16:01:21.96494Z",
            "modified": "2025-09-03T16:01:21.96494Z",
            "name": "C2 URL",
            "description": "Smooth Operator C2 server used for command and control.",
            "pattern": "[url:value = 'https://pbxcloudeservices.com/network']",
            "pattern_type": "stix",
            "pattern_version": "2.1",
            "valid_from": "2025-09-03T16:01:21.964933Z"
        },
        {
            "type": "indicator",
            "spec_version": "2.1",
            "id": "indicator--ee5ef927-1169-40e5-9008-8d8e6da9d96e",
            "created": "2025-09-03T16:01:21.966283Z",
            "modified": "2025-09-03T16:01:21.966283Z",
            "name": "C2 URL",
            "description": "Smooth Operator C2 server used for command and control.",
            "pattern": "[url:value = 'https://pbxphonenetwork.com/phone']",
            "pattern_type": "stix",
            "pattern_version": "2.1",
            "valid_from": "2025-09-03T16:01:21.966275Z"
        },
        {
            "type": "indicator",
            "spec_version": "2.1",
            "id": "indicator--725e9ab8-506f-4a7f-a10d-c61dfa495e69",
            "created": "2025-09-03T16:01:21.967603Z",
            "modified": "2025-09-03T16:01:21.967603Z",
            "name": "C2 URL",
            "description": "Smooth Operator C2 server used for command and control.",
            "pattern": "[url:value = 'https://akamaitechcloudservices.com/v2/fileapi']",
            "pattern_type": "stix",
            "pattern_version": "2.1",
            "valid_from": "2025-09-03T16:01:21.967596Z"
        },
        {
            "type": "indicator",
            "spec_version": "2.1",
            "id": "indicator--ab13d847-e37f-48f4-ad23-6737b56b7f2b",
            "created": "2025-09-03T16:01:21.968916Z",
            "modified": "2025-09-03T16:01:21.968916Z",
            "name": "C2 URL",
            "description": "Smooth Operator C2 server used for command and control.",
            "pattern": "[url:value = 'https://azureonlinestorage.com/google/storage']",
            "pattern_type": "stix",
            "pattern_version": "2.1",
            "valid_from": "2025-09-03T16:01:21.968909Z"
        },
        {
            "type": "indicator",
            "spec_version": "2.1",
            "id": "indicator--de3d0f52-1835-4c58-903e-4838008264d6",
            "created": "2025-09-03T16:01:21.970246Z",
            "modified": "2025-09-03T16:01:21.970246Z",
            "name": "C2 URL",
            "description": "Smooth Operator C2 server used for command and control.",
            "pattern": "[url:value = 'https://msedgepackageinfo.com/ms-webview']",
            "pattern_type": "stix",
            "pattern_version": "2.1",
            "valid_from": "2025-09-03T16:01:21.970239Z"
        },
        {
            "type": "indicator",
            "spec_version": "2.1",
            "id": "indicator--91dce08a-738b-490b-b6e7-0b3681b71144",
            "created": "2025-09-03T16:01:21.971595Z",
            "modified": "2025-09-03T16:01:21.971595Z",
            "name": "C2 URL",
            "description": "Smooth Operator C2 server used for command and control.",
            "pattern": "[url:value = 'https://glcloudservice.com/v1/status']",
            "pattern_type": "stix",
            "pattern_version": "2.1",
            "valid_from": "2025-09-03T16:01:21.971587Z"
        },
        {
            "type": "indicator",
            "spec_version": "2.1",
            "id": "indicator--66ce15bb-8dd3-4824-8033-f4d7b375640a",
            "created": "2025-09-03T16:01:21.97342Z",
            "modified": "2025-09-03T16:01:21.97342Z",
            "name": "C2 URL",
            "description": "Smooth Operator C2 server used for command and control.",
            "pattern": "[url:value = 'https://pbxsources.com/queue']",
            "pattern_type": "stix",
            "pattern_version": "2.1",
            "valid_from": "2025-09-03T16:01:21.973412Z"
        },
        {
            "type": "indicator",
            "spec_version": "2.1",
            "id": "indicator--80e1e57f-42ba-4a47-b719-cd11cf9a1f18",
            "created": "2025-09-03T16:01:21.974774Z",
            "modified": "2025-09-03T16:01:21.974774Z",
            "name": "Exfiltration URL",
            "description": "Smooth Operator exfiltration endpoint used to steal victim data.",
            "pattern": "[url:value = 'https://sbmsa.wiki/blog/_insert']",
            "pattern_type": "stix",
            "pattern_version": "2.1",
            "valid_from": "2025-09-03T16:01:21.974766Z"
        },
        {
            "type": "indicator",
            "spec_version": "2.1",
            "id": "indicator--5f257659-687a-4da4-8779-f0d50dd80149",
            "created": "2025-09-03T16:01:21.975879Z",
            "modified": "2025-09-03T16:01:21.975879Z",
            "name": "Indicator for 3CXDesktopApp-18.12.416.dmg (MD5)",
            "description": "MD5 hash of malicious, trojanised, signed and notarized 3CX software package containing the malicious copy of libffmpeg.dylib.",
            "pattern": "[file:hashes.'MD5' = 'd5101c3b86d973a848ab7ed79cd11e5a']",
            "pattern_type": "stix",
            "pattern_version": "2.1",
            "valid_from": "2025-09-03T16:01:21.975872Z"
        },
        {
            "type": "indicator",
            "spec_version": "2.1",
            "id": "indicator--0fa6a97b-431f-4755-8aca-ce5065ac97ef",
            "created": "2025-09-03T16:01:21.976737Z",
            "modified": "2025-09-03T16:01:21.976737Z",
            "name": "Indicator for 3CXDesktopApp-18.12.416.dmg (SHA1)",
            "description": "SHA-1 hash of malicious, trojanised, signed and notarized 3CX software package containing the malicious copy of libffmpeg.dylib.",
            "pattern": "[file:hashes.'SHA1' = '3dc840d32ce86cebf657b17cef62814646ba8e98']",
            "pattern_type": "stix",
            "pattern_version": "2.1",
            "valid_from": "2025-09-03T16:01:21.976729Z"
        },
        {
            "type": "indicator",
            "spec_version": "2.1",
            "id": "indicator--82e339c5-ecf7-41a4-a307-b8360d0c3906",
            "created": "2025-09-03T16:01:21.977595Z",
            "modified": "2025-09-03T16:01:21.977595Z",
            "name": "Indicator for 3CXDesktopApp-18.12.416.dmg (SHA256)",
            "description": "SHA-256 hash of malicious, trojanised, signed and notarized 3CX software package containing the malicious copy of libffmpeg.dylib.",
            "pattern": "[file:hashes.'SHA256' = 'e6bbc33815b9f20b0cf832d7401dd893fbc467c800728b5891336706da0dbcec']",
            "pattern_type": "stix",
            "pattern_version": "2.1",
            "valid_from": "2025-09-03T16:01:21.977587Z"
        },
        {
            "type": "indicator",
            "spec_version": "2.1",
            "id": "indicator--923fe82f-3cd7-4847-8c3a-ffb924b15c60",
            "created": "2025-09-03T16:01:21.978455Z",
            "modified": "2025-09-03T16:01:21.978455Z",
            "name": "Indicator for libffmpeg.dylib (MD5)",
            "description": "MD5 hash of Smooth Operator universal binary packaged inside the malicious 3CX disk image.",
            "pattern": "[file:hashes.'MD5' = '660ea9b8205fbd2da59fefd26ae5115c']",
            "pattern_type": "stix",
            "pattern_version": "2.1",
            "valid_from": "2025-09-03T16:01:21.978447Z"
        },
        {
            "type": "indicator",
            "spec_version": "2.1",
            "id": "indicator--1dbf6839-dd3c-4ea6-a23e-72ff3e3d673a",
            "created": "2025-09-03T16:01:21.979255Z",
            "modified": "2025-09-03T16:01:21.979255Z",
            "name": "Indicator for libffmpeg.dylib (SHA1)",
            "description": "SHA-1 hash of Smooth Operator universal binary packaged inside the malicious 3CX disk image.",
            "pattern": "[file:hashes.'SHA1' = '769383fc65d1386dd141c960c9970114547da0c2']",
            "pattern_type": "stix",
            "pattern_version": "2.1",
            "valid_from": "2025-09-03T16:01:21.979247Z"
        },
        {
            "type": "indicator",
            "spec_version": "2.1",
            "id": "indicator--e28df472-b0fa-44aa-a6c8-01750564d8c1",
            "created": "2025-09-03T16:01:21.980249Z",
            "modified": "2025-09-03T16:01:21.980249Z",
            "name": "Indicator for libffmpeg.dylib (SHA256)",
            "description": "SHA-256 hash of Smooth Operator universal binary packaged inside the malicious 3CX disk image.",
            "pattern": "[file:hashes.'SHA256' = 'a64fa9f1c76457ecc58402142a8728ce34ccba378c17318b3340083eeb7acc67']",
            "pattern_type": "stix",
            "pattern_version": "2.1",
            "valid_from": "2025-09-03T16:01:21.980239Z"
        },
        {
            "type": "indicator",
            "spec_version": "2.1",
            "id": "indicator--7b183e8b-314f-4e0e-b979-d037b1683cfa",
            "created": "2025-09-03T16:01:21.981208Z",
            "modified": "2025-09-03T16:01:21.981208Z",
            "name": "Indicator for UpdateAgent (MD5)",
            "description": "MD5 hash of Smooth Operator second-stage payload which exfiltrates 3CX victim data.",
            "pattern": "[file:hashes.'MD5' = '5faf36ca90f6406a78124f538a03387a']",
            "pattern_type": "stix",
            "pattern_version": "2.1",
            "valid_from": "2025-09-03T16:01:21.981199Z"
        },
        {
            "type": "indicator",
            "spec_version": "2.1",
            "id": "indicator--60a8c520-87a6-4f85-a03e-d13649cc00b9",
            "created": "2025-09-03T16:01:21.982444Z",
            "modified": "2025-09-03T16:01:21.982444Z",
            "name": "Indicator for UpdateAgent (SHA1)",
            "description": "SHA-1 hash of Smooth Operator second-stage payload which exfiltrates 3CX victim data.",
            "pattern": "[file:hashes.'SHA1' = '9e9a5f8d86356796162cee881c843cde9eaedfb3']",
            "pattern_type": "stix",
            "pattern_version": "2.1",
            "valid_from": "2025-09-03T16:01:21.982434Z"
        },
        {
            "type": "indicator",
            "spec_version": "2.1",
            "id": "indicator--48d064d2-2a75-4b09-a6d9-34a02d2323ae",
            "created": "2025-09-03T16:01:21.983266Z",
            "modified": "2025-09-03T16:01:21.983266Z",
            "name": "Indicator for UpdateAgent (SHA256)",
            "description": "SHA-256 hash of Smooth Operator second-stage payload which exfiltrates 3CX victim data.",
            "pattern": "[file:hashes.'SHA256' = '6c121f2b2efa6592c2c22b29218157ec9e63f385e7a1d7425857d603ddef8c59']",
            "pattern_type": "stix",
            "pattern_version": "2.1",
            "valid_from": "2025-09-03T16:01:21.983259Z"
        },
        {
            "type": "relationship",
            "spec_version": "2.1",
            "id": "relationship--6d72f72c-c509-47dc-bb01-bb589fbd9faf",
            "created": "2025-09-03T16:01:21.953156Z",
            "modified": "2025-09-03T16:01:21.953156Z",
            "relationship_type": "based-on",
            "source_ref": "indicator--34d4da07-0522-4e8a-99e9-960a0b332111",
            "target_ref": "url--3ca77848-3c86-5177-b9c7-262d440d813f"
        },
        {
            "type": "relationship",
            "spec_version": "2.1",
            "id": "relationship--1f006d62-4bad-4373-bdc2-2e6a18f90eb9",
            "created": "2025-09-03T16:01:21.954875Z",
            "modified": "2025-09-03T16:01:21.954875Z",
            "relationship_type": "based-on",
            "source_ref": "indicator--a3406e06-71ce-4cac-b448-093cf9067923",
            "target_ref": "url--3ce4a838-3d16-5dae-a0e0-e04cd86b5de5"
        },
        {
            "type": "relationship",
            "spec_version": "2.1",
            "id": "relationship--85e0b11e-430f-4a07-be97-66f9a82822a8",
            "created": "2025-09-03T16:01:21.956506Z",
            "modified": "2025-09-03T16:01:21.956506Z",
            "relationship_type": "based-on",
            "source_ref": "indicator--283ce6c3-0eb9-4277-8b1a-a8de401eef30",
            "target_ref": "url--c0df7321-5a23-5833-a830-d26ac9be888a"
        },
        {
            "type": "relationship",
            "spec_version": "2.1",
            "id": "relationship--50e38c24-292b-44c6-b145-cf9897ce8c22",
            "created": "2025-09-03T16:01:21.958055Z",
            "modified": "2025-09-03T16:01:21.958055Z",
            "relationship_type": "based-on",
            "source_ref": "indicator--b73e98d7-bee5-4404-8eb1-4b876bab4588",
            "target_ref": "url--9bb50a9b-3b49-5ec4-bd4b-f6218f0a3291"
        },
        {
            "type": "relationship",
            "spec_version": "2.1",
            "id": "relationship--a3a5bee6-6c10-4357-9bd6-96ba3aea7bc5",
            "created": "2025-09-03T16:01:21.959602Z",
            "modified": "2025-09-03T16:01:21.959602Z",
            "relationship_type": "based-on",
            "source_ref": "indicator--bf86823d-fd0f-4c75-9ac4-f4177af58ea8",
            "target_ref": "url--dbe40f12-c563-5543-859e-b7e68f643b2e"
        },
        {
            "type": "relationship",
            "spec_version": "2.1",
            "id": "relationship--6bf29b02-f240-430a-a40f-338d7e01fd14",
            "created": "2025-09-03T16:01:21.961148Z",
            "modified": "2025-09-03T16:01:21.961148Z",
            "relationship_type": "based-on",
            "source_ref": "indicator--48f74225-c480-4404-b8c0-118de8de833c",
            "target_ref": "url--7fdbe136-4ff2-52f3-a597-f76d4438fdfd"
        },
        {
            "type": "relationship",
            "spec_version": "2.1",
            "id": "relationship--822694a8-bb0d-43ba-846a-7e1a806f5cfe",
            "created": "2025-09-03T16:01:21.962967Z",
            "modified": "2025-09-03T16:01:21.962967Z",
            "relationship_type": "based-on",
            "source_ref": "indicator--5acc1604-8dc7-4596-aeb5-f750ff08e7d8",
            "target_ref": "url--67d95451-80b8-5473-bb76-d2120307ba1b"
        },
        {
            "type": "relationship",
            "spec_version": "2.1",
            "id": "relationship--8c2c1575-3baf-4abd-8c97-bde61bf06974",
            "created": "2025-09-03T16:01:21.964391Z",
            "modified": "2025-09-03T16:01:21.964391Z",
            "relationship_type": "based-on",
            "source_ref": "indicator--3241cd79-ce7b-4846-bc5d-d76743b08873",
            "target_ref": "url--e6657594-2903-51f3-87db-e23c6b55deef"
        },
        {
            "type": "relationship",
            "spec_version": "2.1",
            "id": "relationship--78b06ad9-4547-42ec-8ae3-d6c6aeebb764",
            "created": "2025-09-03T16:01:21.965753Z",
            "modified": "2025-09-03T16:01:21.965753Z",
            "relationship_type": "based-on",
            "source_ref": "indicator--2bb3af37-3765-4530-84aa-db9924b5944c",
            "target_ref": "url--3ea4b73b-cfa2-58dc-9dc7-1cff719316d6"
        },
        {
            "type": "relationship",
            "spec_version": "2.1",
            "id": "relationship--7ce83242-74e3-4151-9232-1a472510d823",
            "created": "2025-09-03T16:01:21.967076Z",
            "modified": "2025-09-03T16:01:21.967076Z",
            "relationship_type": "based-on",
            "source_ref": "indicator--ee5ef927-1169-40e5-9008-8d8e6da9d96e",
            "target_ref": "url--8096d021-fbde-5c5c-bdde-579339fed002"
        },
        {
            "type": "relationship",
            "spec_version": "2.1",
            "id": "relationship--d7f19581-973c-49e6-a308-54105415b5e2",
            "created": "2025-09-03T16:01:21.968398Z",
            "modified": "2025-09-03T16:01:21.968398Z",
            "relationship_type": "based-on",
            "source_ref": "indicator--725e9ab8-506f-4a7f-a10d-c61dfa495e69",
            "target_ref": "url--d4c0c66e-acd2-52b3-b82b-eeb29120e0c6"
        },
        {
            "type": "relationship",
            "spec_version": "2.1",
            "id": "relationship--0b17ad7b-0621-4061-955d-cd908b987d17",
            "created": "2025-09-03T16:01:21.969723Z",
            "modified": "2025-09-03T16:01:21.969723Z",
            "relationship_type": "based-on",
            "source_ref": "indicator--ab13d847-e37f-48f4-ad23-6737b56b7f2b",
            "target_ref": "url--62529b3b-96ed-53cf-938e-ae44eca99914"
        },
        {
            "type": "relationship",
            "spec_version": "2.1",
            "id": "relationship--ccdbb85b-d569-4d16-865e-62458e2c131a",
            "created": "2025-09-03T16:01:21.971024Z",
            "modified": "2025-09-03T16:01:21.971024Z",
            "relationship_type": "based-on",
            "source_ref": "indicator--de3d0f52-1835-4c58-903e-4838008264d6",
            "target_ref": "url--6d15f2ac-747b-5b8c-8325-f9994aaf02ee"
        },
        {
            "type": "relationship",
            "spec_version": "2.1",
            "id": "relationship--57288741-53fa-47b8-86cc-4323a9ed5066",
            "created": "2025-09-03T16:01:21.972723Z",
            "modified": "2025-09-03T16:01:21.972723Z",
            "relationship_type": "based-on",
            "source_ref": "indicator--91dce08a-738b-490b-b6e7-0b3681b71144",
            "target_ref": "url--230a9427-bc2b-56b1-96a0-5d6274096e11"
        },
        {
            "type": "relationship",
            "spec_version": "2.1",
            "id": "relationship--505bab61-df92-4ae5-a44f-5be10b18e3ea",
            "created": "2025-09-03T16:01:21.974197Z",
            "modified": "2025-09-03T16:01:21.974197Z",
            "relationship_type": "based-on",
            "source_ref": "indicator--66ce15bb-8dd3-4824-8033-f4d7b375640a",
            "target_ref": "url--4523eebd-2121-542b-9aef-3fdaf7184a3f"
        },
        {
            "type": "relationship",
            "spec_version": "2.1",
            "id": "relationship--9df15e70-d11e-4eba-be0d-14a735718662",
            "created": "2025-09-03T16:01:21.975551Z",
            "modified": "2025-09-03T16:01:21.975551Z",
            "relationship_type": "based-on",
            "source_ref": "indicator--80e1e57f-42ba-4a47-b719-cd11cf9a1f18",
            "target_ref": "url--a91f7562-d8f2-5f71-b267-2be460045132"
        },
        {
            "type": "relationship",
            "spec_version": "2.1",
            "id": "relationship--01e0dfec-87c0-475c-a08c-445831a26455",
            "created": "2025-09-03T16:01:21.984131Z",
            "modified": "2025-09-03T16:01:21.984131Z",
            "relationship_type": "derived-from",
            "source_ref": "indicator--5f257659-687a-4da4-8779-f0d50dd80149",
            "target_ref": "indicator--0fa6a97b-431f-4755-8aca-ce5065ac97ef"
        },
        {
            "type": "relationship",
            "spec_version": "2.1",
            "id": "relationship--473cc04c-f229-4a45-ab48-aa63547dea59",
            "created": "2025-09-03T16:01:21.98445Z",
            "modified": "2025-09-03T16:01:21.98445Z",
            "relationship_type": "derived-from",
            "source_ref": "indicator--5f257659-687a-4da4-8779-f0d50dd80149",
            "target_ref": "indicator--82e339c5-ecf7-41a4-a307-b8360d0c3906"
        },
        {
            "type": "relationship",
            "spec_version": "2.1",
            "id": "relationship--878b89e5-130e-4365-91ad-db326ba88707",
            "created": "2025-09-03T16:01:21.984687Z",
            "modified": "2025-09-03T16:01:21.984687Z",
            "relationship_type": "derived-from",
            "source_ref": "indicator--0fa6a97b-431f-4755-8aca-ce5065ac97ef",
            "target_ref": "indicator--82e339c5-ecf7-41a4-a307-b8360d0c3906"
        },
        {
            "type": "relationship",
            "spec_version": "2.1",
            "id": "relationship--3710aef7-16aa-48d8-8a3c-0b9d03f2fbdc",
            "created": "2025-09-03T16:01:21.98493Z",
            "modified": "2025-09-03T16:01:21.98493Z",
            "relationship_type": "derived-from",
            "source_ref": "indicator--923fe82f-3cd7-4847-8c3a-ffb924b15c60",
            "target_ref": "indicator--1dbf6839-dd3c-4ea6-a23e-72ff3e3d673a"
        },
        {
            "type": "relationship",
            "spec_version": "2.1",
            "id": "relationship--148547f5-69a2-4bd0-b9e7-faf0db3422d7",
            "created": "2025-09-03T16:01:21.985179Z",
            "modified": "2025-09-03T16:01:21.985179Z",
            "relationship_type": "derived-from",
            "source_ref": "indicator--923fe82f-3cd7-4847-8c3a-ffb924b15c60",
            "target_ref": "indicator--e28df472-b0fa-44aa-a6c8-01750564d8c1"
        },
        {
            "type": "relationship",
            "spec_version": "2.1",
            "id": "relationship--c8cd1bb8-e6d8-4507-9daf-1f9c2a33aebc",
            "created": "2025-09-03T16:01:21.985467Z",
            "modified": "2025-09-03T16:01:21.985467Z",
            "relationship_type": "derived-from",
            "source_ref": "indicator--1dbf6839-dd3c-4ea6-a23e-72ff3e3d673a",
            "target_ref": "indicator--e28df472-b0fa-44aa-a6c8-01750564d8c1"
        },
        {
            "type": "relationship",
            "spec_version": "2.1",
            "id": "relationship--b59f6c6c-a4a8-42ea-950b-499c1d3adf80",
            "created": "2025-09-03T16:01:21.985708Z",
            "modified": "2025-09-03T16:01:21.985708Z",
            "relationship_type": "derived-from",
            "source_ref": "indicator--7b183e8b-314f-4e0e-b979-d037b1683cfa",
            "target_ref": "indicator--60a8c520-87a6-4f85-a03e-d13649cc00b9"
        },
        {
            "type": "relationship",
            "spec_version": "2.1",
            "id": "relationship--ba17838b-27ac-4ddd-83ea-b7840396a445",
            "created": "2025-09-03T16:01:21.985956Z",
            "modified": "2025-09-03T16:01:21.985956Z",
            "relationship_type": "derived-from",
            "source_ref": "indicator--7b183e8b-314f-4e0e-b979-d037b1683cfa",
            "target_ref": "indicator--48d064d2-2a75-4b09-a6d9-34a02d2323ae"
        },
        {
            "type": "relationship",
            "spec_version": "2.1",
            "id": "relationship--7c09ccb5-e7e9-4f7e-856b-14a38b0b4ef7",
            "created": "2025-09-03T16:01:21.98621Z",
            "modified": "2025-09-03T16:01:21.98621Z",
            "relationship_type": "derived-from",
            "source_ref": "indicator--60a8c520-87a6-4f85-a03e-d13649cc00b9",
            "target_ref": "indicator--48d064d2-2a75-4b09-a6d9-34a02d2323ae"
        },
        {
            "type": "malware",
            "spec_version": "2.1",
            "id": "malware--d6bba528-b310-49d2-bc39-0e95e11d0a3a",
            "created_by_ref": "identity--0581a0ae-0be3-473a-a9fe-eb784433f1fa",
            "created": "2025-09-03T16:02:49.417718Z",
            "modified": "2025-09-03T16:02:49.417718Z",
            "name": "smooth operator",
            "description": "Smooth Operator is a macOS supply chain malware distributed as part of the 3CX supply chain attack. It infects victims via trojanised, signed, and notarized 3CX software packages, specifically targeting macOS systems. The malware consists of two stages: the first-stage is compiled into a dynamic library (libffmpeg.dylib) and distributed with the 3CX software, while the second-stage (UpdateAgent) is downloaded and executed by the first-stage. Smooth Operator exfiltrates victim data using a custom data encoding algorithm over HTTPS, randomises its C2 server selection, and implements various evasion and persistence techniques. It collects device information, exfiltrates data from 3CX configuration files, and deletes itself after execution to evade detection.",
            "malware_types": [
                "remote-access-trojan",
                "backdoor",
                "downloader",
                "spyware",
                "ransomware"
            ],
            "is_family": true
        },
        {
            "type": "malware",
            "spec_version": "2.1",
            "id": "malware--73ae42a4-0657-4684-8cf9-7072f1b0167f",
            "created_by_ref": "identity--0581a0ae-0be3-473a-a9fe-eb784433f1fa",
            "created": "2025-09-03T16:02:49.418425Z",
            "modified": "2025-09-03T16:02:49.418425Z",
            "name": "updateagent",
            "description": "UpdateAgent is the second-stage payload of Smooth Operator, executed on Intel x86_64 macOS systems. It exfiltrates victim data from 3CX configuration files, parses and extracts domain and account name values, and sends them to the C2 server using a custom obfuscation algorithm. The binary deletes itself from disk immediately after execution and is not notarized.",
            "malware_types": [
                "spyware",
                "downloader"
            ],
            "is_family": true
        },
        {
            "type": "identity",
            "spec_version": "2.1",
            "id": "identity--f728f373-1940-4acf-aa55-3e64f77092c7",
            "created": "2025-09-03T16:02:49.418767Z",
            "modified": "2025-09-03T16:02:49.418767Z",
            "name": "3CX",
            "description": "3CX is the legitimate software vendor whose supply chain was compromised, resulting in the distribution of trojanised software packages containing Smooth Operator malware.",
            "identity_class": "organization"
        },
        {
            "type": "identity",
            "spec_version": "2.1",
            "id": "identity--4a4837d4-0963-4274-af89-6eb311ca6054",
            "created": "2025-09-03T16:02:49.41922Z",
            "modified": "2025-09-03T16:02:49.41922Z",
            "name": "Apple",
            "description": "Apple is referenced as the platform provider for macOS, whose notarization process was abused to distribute the trojanised 3CX software package containing Smooth Operator.",
            "identity_class": "organization"
        },
        {
            "type": "indicator",
            "spec_version": "2.1",
            "id": "indicator--d8fe363e-e12f-4cd8-a397-c4155b2a2903",
            "created_by_ref": "identity--0581a0ae-0be3-473a-a9fe-eb784433f1fa",
            "created": "2025-09-03T16:02:49.419521Z",
            "modified": "2025-09-03T16:02:49.419521Z",
            "name": "Smooth_Operator_Obfuscation",
            "description": "YARA rule to detect related activity.",
            "pattern": "rule Smooth_Operator_Obfuscation {\n    meta:\n        author = \"NCSC\"\n        description = \"This rule identifies unique strings and code\npresent in the C2 string obfuscation code of Smooth Operator.\"\n        date = \"2023-06-29\"\n        hash1 = \"769383fc65d1386dd141c960c9970114547da0c2\"\n        hash2 = \"9e9a5f8d86356796162cee881c843cde9eaedfb3\"\n\n    strings:\n\n    $ = {48 69 ?? 61 60 60 60 48 89 ?? 48 C1 EA 3F 48 C1 ?? 25 01\n\n?? 6B ?? 55}\n\n$ = \"!#$%&()*+-\n\n.0123456789:;<>?@ABCDEFGHIJKLMNOPQRSTUVWXYZ[]_abcdefghi\"\n$ = {3E00C7[5-6]26706572} // &per\n$ = {3E00C7[5-6]26646F6C} // &dol\n$ = {75733E00C7[5-6]26706C75} // &plus\n$ = {6D693E00C7[5-6]2673656D} // &semi\n\n    condition:\n\n    ((uint32(0) == 0xFEEDFACF) or (uint32(0) == 0xFEEDFACE) or\n\n(uint32(0) == 0xCAFEBABE) or (uint32(0) == 0xCAFEBABF)) and all of them\n}",
            "pattern_type": "yara",
            "valid_from": "2025-09-03T16:02:49.41951Z"
        },
        {
            "type": "indicator",
            "spec_version": "2.1",
            "id": "indicator--8c20ca67-7a6b-4463-a3db-30a5fa979760",
            "created_by_ref": "identity--0581a0ae-0be3-473a-a9fe-eb784433f1fa",
            "created": "2025-09-03T16:02:49.419859Z",
            "modified": "2025-09-03T16:02:49.419859Z",
            "name": "Smooth_Operator_Obfuscation_2",
            "description": "YARA rule to detect related activity.",
            "pattern": "rule Smooth_Operator_Obfuscation_2 {\n    meta:\n        author = \"NCSC\"\n        description = \"This rule identifies unique code sections in the\nC2 string obfuscation algorithm.\"\n        date = \"2023-06-29\"\n        hash1 = \"769383fc65d1386dd141c960c9970114547da0c2\"\n        hash2 = \"9e9a5f8d86356796162cee881c843cde9eaedfb3\"\n\n    strings:\n        $a_1 = {4869C8616060604889CA48C1EA3F48C1F92501D16BC95529C8[0-\n3]83F807}\n        $b_1 = {438D1C24F7DB41F7DC} // neg\n        $b_2 = {478D3C3641F7DF41F7DE} // neg\n\n    condition:\n        ((uint32(0) == 0xFEEDFACF) or (uint32(0) == 0xFEEDFACE) or\n(uint32(0) == 0xCAFEBABE) or (uint32(0) == 0xCAFEBABF)) and any of ($b*)\nand $a_1\n}",
            "pattern_type": "yara",
            "valid_from": "2025-09-03T16:02:49.419852Z"
        },
        {
            "type": "indicator",
            "spec_version": "2.1",
            "id": "indicator--f8e3c02f-7900-4c89-8f76-1d6865303f89",
            "created_by_ref": "identity--0581a0ae-0be3-473a-a9fe-eb784433f1fa",
            "created": "2025-09-03T16:02:49.420145Z",
            "modified": "2025-09-03T16:02:49.420145Z",
            "name": "Smooth_Operator_Strings",
            "description": "YARA rule to detect related activity.",
            "pattern": "rule Smooth_Operator_Strings {\n    meta:\n        author = \"NCSC\"\n        description = \"This rule identifies broader functionality across\nSmooth Operator, identifying strings observed throughout.\"\n        date = \"2023-06-29\"\n        hash1 = \"769383fc65d1386dd141c960c9970114547da0c2\"\n\n    strings:\n        $ = {80 [2] 7A 48 FF C0 48 83 F8 38} // .main_storage XOR loop\n        $ = \"<key>ProductVersion</key>\"\n        $ = \".session-lock\"\n        $ = \"%s/.main_storage\"\n        $ = \"%s/UpdateAgent\"\n        $ =\n{3715001316161B554F544A5A522D13141E150D095A342E5A4B4A544A415A2D13144C4E41\n5A024C4E535A3B0A0A161F2D1F1831130E554F494D54494C5A5231322E3736565A1613111\nF5A3D1F191115535A39120815171F554B4A42544A544F494F43544B48425A291B1C1B0813\n554F494D54494C} // XOR'd UA\n        $ = {B02D[0-8]88470888470D884712884717C6472400} // victim ID\ngeneration\n\n    condition:\n\n((uint32(0) == 0xFEEDFACF) or (uint32(0) == 0xFEEDFACE) or\n(uint32(0) == 0xCAFEBABE) or (uint32(0) == 0xCAFEBABF)) and 4 of them\n}",
            "pattern_type": "yara",
            "valid_from": "2025-09-03T16:02:49.420138Z"
        },
        {
            "type": "indicator",
            "spec_version": "2.1",
            "id": "indicator--117843eb-9f5b-4533-b47c-aa29fd4c6954",
            "created_by_ref": "identity--0581a0ae-0be3-473a-a9fe-eb784433f1fa",
            "created": "2025-09-03T16:02:49.420465Z",
            "modified": "2025-09-03T16:02:49.420465Z",
            "name": "Smooth_Operator_C2_codes",
            "description": "YARA rule to detect related activity.",
            "pattern": "rule Smooth_Operator_C2_codes {\n    meta:\n        author = \"NCSC\"\n        description = \"This rule identifies sections of code which are\nresponsible for parsing tasking command codes in Smooth Operator.\"\n        date = \"2023-06-29\"\n        hash1 = \"769383fc65d1386dd141c960c9970114547da0c2\"\n\n    strings:\n\n$ = {80340F7A48FFC14839C8} // XOR deobfuscate tasking\n\n        $ = {8B073D4938000074??3D018000008B4C24??0F[3-6]3D01900000} // C2\ncodes\n\n    condition:\n\n((uint32(0) == 0xFEEDFACF) or (uint32(0) == 0xFEEDFACE) or\n(uint32(0) == 0xCAFEBABE) or (uint32(0) == 0xCAFEBABF)) and all of them\n}",
            "pattern_type": "yara",
            "valid_from": "2025-09-03T16:02:49.420459Z"
        },
        {
            "type": "indicator",
            "spec_version": "2.1",
            "id": "indicator--7314879c-9085-4111-99fc-2d41961d4a4f",
            "created_by_ref": "identity--0581a0ae-0be3-473a-a9fe-eb784433f1fa",
            "created": "2025-09-03T16:02:49.420865Z",
            "modified": "2025-09-03T16:02:49.420865Z",
            "name": "Smooth_Operator_Sleeps",
            "description": "YARA rule to detect related activity.",
            "pattern": "rule Smooth_Operator_Sleeps {\n    meta:\n        author = \"NCSC\"\n        description = \"This rule identifies algorithms used by the\nmalware developer to generate random time values in Smooth Operator.\"\n        date = \"2023-06-29\"\n        hash1 = \"769383fc65d1386dd141c960c9970114547da0c2\"\n\n    strings:\n\n$ =\n\n{E8[4]E8[4]89C14869C93FC5254348C1E9246BC93D29C86BE83C81C5100E0000B80F0000\n00} // between beacon time generation\n\n$ = {E8[4]E8[4]89C1490FAFCE48C1E9238D0C898D0C4929C8} // C2 index\n$ =\n\n{89E8D1E841BE932449924C0FAFF049C1EE224489F0C1E0044489F129C14101EE4101CE48\n8DBC24[4]4C892FE8} // initial sleep\n\n    condition:\n        ((uint32(0) == 0xFEEDFACF) or (uint32(0) == 0xFEEDFACE) or\n(uint32(0) == 0xCAFEBABE) or (uint32(0) == 0xCAFEBABF)) and any of them\n}",
            "pattern_type": "yara",
            "valid_from": "2025-09-03T16:02:49.420854Z"
        },
        {
            "type": "indicator",
            "spec_version": "2.1",
            "id": "indicator--5218bc5c-e59b-4fa3-be17-ffa88ac4d177",
            "created_by_ref": "identity--0581a0ae-0be3-473a-a9fe-eb784433f1fa",
            "created": "2025-09-03T16:02:49.421167Z",
            "modified": "2025-09-03T16:02:49.421167Z",
            "name": "Smooth_Operator_II",
            "description": "YARA rule to detect related activity.",
            "pattern": "rule Smooth_Operator_II {\n    meta:\n        author = \"NCSC\"\n        description = \"This rule identifies strings observed in the\nsecond stage of Smooth Operator.\"\n        date = \"2023-06-29\"\n        hash1 = \"9e9a5f8d86356796162cee881c843cde9eaedfb3\"\n\n    strings:\n        $ = \"3cx_auth_id=%s;3cx_auth_token_content=%s;__tutma=true\"\n\n  $ = \"AccountName\\\":\"\n\n        $ = \"url\\\": \\\"https://\"\n        $ = \"%s/Library/Application Support/3CX Desktop\nApp/.main_storage\"\n        $ = \"%s/Library/Application Support/3CX Desktop App/config.json\"\n        $ = \"read_config\"\n        $ = \"enc_text\"\n        $ = \"send_post\"\n        $ = \"parse_json_config\"\n\n    condition:\n\n    ((uint32(0) == 0xFEEDFACF) or (uint32(0) == 0xFEEDFACE) or\n\n(uint32(0) == 0xCAFEBABE) or (uint32(0) == 0xCAFEBABF)) and 5 of them\n}",
            "pattern_type": "yara",
            "valid_from": "2025-09-03T16:02:49.421161Z"
        },
        {
            "type": "attack-pattern",
            "spec_version": "2.1",
            "id": "attack-pattern--d770181c-ec4b-4d46-861e-7a3253f1b884",
            "created_by_ref": "identity--0581a0ae-0be3-473a-a9fe-eb784433f1fa",
            "created": "2025-09-03T16:02:49.421488Z",
            "modified": "2025-09-03T16:02:49.421488Z",
            "name": "Supply Chain Compromise: Compromise Software Dependencies and Development Tools",
            "description": "Smooth Operator is distributed via legitimate channels as trojanised, signed and notarized 3CX software.",
            "kill_chain_phases": [
                {
                    "kill_chain_name": "mitre-attack",
                    "phase_name": "initial access"
                }
            ],
            "external_references": [
                {
                    "source_name": "mitre-attack",
                    "url": "https://attack.mitre.org/techniques/T1195/001",
                    "external_id": "T1195.001"
                }
            ]
        },
        {
            "type": "attack-pattern",
            "spec_version": "2.1",
            "id": "attack-pattern--b6660b88-6f3c-44cc-9a6f-ab5a8392a0bd",
            "created_by_ref": "identity--0581a0ae-0be3-473a-a9fe-eb784433f1fa",
            "created": "2025-09-03T16:02:49.421982Z",
            "modified": "2025-09-03T16:02:49.421982Z",
            "name": "Compromise Client Software Binary",
            "description": "Smooth Operator runs as part of the 3CX software.",
            "kill_chain_phases": [
                {
                    "kill_chain_name": "mitre-attack",
                    "phase_name": "persistence"
                }
            ],
            "external_references": [
                {
                    "source_name": "mitre-attack",
                    "url": "https://attack.mitre.org/techniques/T1554",
                    "external_id": "T1554"
                }
            ]
        },
        {
            "type": "attack-pattern",
            "spec_version": "2.1",
            "id": "attack-pattern--2077f92b-a864-4aa7-a53d-c326ff66f115",
            "created_by_ref": "identity--0581a0ae-0be3-473a-a9fe-eb784433f1fa",
            "created": "2025-09-03T16:02:49.42238Z",
            "modified": "2025-09-03T16:02:49.42238Z",
            "name": "Deobfuscate/Decode Files or Information",
            "description": "Smooth Operator uses a custom algorithm to obfuscate data exfiltrated over the C2 channel. Smooth Operator deobfuscates data it writes to a file on disk as well as tasking responses.",
            "kill_chain_phases": [
                {
                    "kill_chain_name": "mitre-attack",
                    "phase_name": "defence evasion"
                }
            ],
            "external_references": [
                {
                    "source_name": "mitre-attack",
                    "url": "https://attack.mitre.org/techniques/T1140",
                    "external_id": "T1140"
                }
            ]
        },
        {
            "type": "attack-pattern",
            "spec_version": "2.1",
            "id": "attack-pattern--863f75b6-ea4a-4042-ae1c-91fe3cdc0b23",
            "created_by_ref": "identity--0581a0ae-0be3-473a-a9fe-eb784433f1fa",
            "created": "2025-09-03T16:02:49.422735Z",
            "modified": "2025-09-03T16:02:49.422735Z",
            "name": "Indicator Removal: File Deletion",
            "description": "Smooth Operator\u2019s second-stage deletes itself from disk immediately on execution.",
            "kill_chain_phases": [
                {
                    "kill_chain_name": "mitre-attack",
                    "phase_name": "defence evasion"
                }
            ],
            "external_references": [
                {
                    "source_name": "mitre-attack",
                    "url": "https://attack.mitre.org/techniques/T1070/004",
                    "external_id": "T1070.004"
                }
            ]
        },
        {
            "type": "attack-pattern",
            "spec_version": "2.1",
            "id": "attack-pattern--b96bf485-0431-45d5-8e9a-fccf58687d43",
            "created_by_ref": "identity--0581a0ae-0be3-473a-a9fe-eb784433f1fa",
            "created": "2025-09-03T16:02:49.423097Z",
            "modified": "2025-09-03T16:02:49.423097Z",
            "name": "Virtualization/Sandbox Evasion: Time Based Evasion",
            "description": "Smooth Operator sleeps for, at minimum, a week before beaconing.",
            "kill_chain_phases": [
                {
                    "kill_chain_name": "mitre-attack",
                    "phase_name": "defence evasion"
                }
            ],
            "external_references": [
                {
                    "source_name": "mitre-attack",
                    "url": "https://attack.mitre.org/techniques/T1497/003",
                    "external_id": "T1497.003"
                }
            ]
        },
        {
            "type": "attack-pattern",
            "spec_version": "2.1",
            "id": "attack-pattern--91b75f4f-2413-4ebd-bd0a-5b6c582f75fa",
            "created_by_ref": "identity--0581a0ae-0be3-473a-a9fe-eb784433f1fa",
            "created": "2025-09-03T16:02:49.423765Z",
            "modified": "2025-09-03T16:02:49.423765Z",
            "name": "Automated Collection",
            "description": "Smooth Operator stages collect data from the victim machine to be included in a beacon or exfiltration.",
            "kill_chain_phases": [
                {
                    "kill_chain_name": "mitre-attack",
                    "phase_name": "collection"
                }
            ],
            "external_references": [
                {
                    "source_name": "mitre-attack",
                    "url": "https://attack.mitre.org/techniques/T1119",
                    "external_id": "T1119"
                }
            ]
        },
        {
            "type": "attack-pattern",
            "spec_version": "2.1",
            "id": "attack-pattern--5972dad2-46b7-479f-a7a6-b33869705a61",
            "created_by_ref": "identity--0581a0ae-0be3-473a-a9fe-eb784433f1fa",
            "created": "2025-09-03T16:02:49.424742Z",
            "modified": "2025-09-03T16:02:49.424742Z",
            "name": "Application Layer Protocol: Web Protocols",
            "description": "Smooth Operator command and control is over HTTPS.",
            "kill_chain_phases": [
                {
                    "kill_chain_name": "mitre-attack",
                    "phase_name": "command and control"
                }
            ],
            "external_references": [
                {
                    "source_name": "mitre-attack",
                    "url": "https://attack.mitre.org/techniques/T1071/001",
                    "external_id": "T1071.001"
                }
            ]
        },
        {
            "type": "attack-pattern",
            "spec_version": "2.1",
            "id": "attack-pattern--8f8c7403-a552-4418-b9a0-88aa997ea801",
            "created_by_ref": "identity--0581a0ae-0be3-473a-a9fe-eb784433f1fa",
            "created": "2025-09-03T16:02:49.425396Z",
            "modified": "2025-09-03T16:02:49.425396Z",
            "name": "Fallback Channels",
            "description": "Smooth Operator contains multiple C2 servers and randomly chooses a new server from the list for each beacon, if one fails it will try another.",
            "kill_chain_phases": [
                {
                    "kill_chain_name": "mitre-attack",
                    "phase_name": "command and control"
                }
            ],
            "external_references": [
                {
                    "source_name": "mitre-attack",
                    "url": "https://attack.mitre.org/techniques/T1008",
                    "external_id": "T1008"
                }
            ]
        },
        {
            "type": "attack-pattern",
            "spec_version": "2.1",
            "id": "attack-pattern--173212d5-ac35-4839-b2eb-74038a88f433",
            "created_by_ref": "identity--0581a0ae-0be3-473a-a9fe-eb784433f1fa",
            "created": "2025-09-03T16:02:49.42592Z",
            "modified": "2025-09-03T16:02:49.42592Z",
            "name": "Automated Exfiltration",
            "description": "Smooth Operator exfiltrates automatically collected data, not over the existing C2 channel.",
            "kill_chain_phases": [
                {
                    "kill_chain_name": "mitre-attack",
                    "phase_name": "exfiltration"
                }
            ],
            "external_references": [
                {
                    "source_name": "mitre-attack",
                    "url": "https://attack.mitre.org/techniques/T1020",
                    "external_id": "T1020"
                }
            ]
        },
        {
            "type": "relationship",
            "spec_version": "2.1",
            "id": "relationship--6f17d42d-8c99-421c-85a2-e32d803c665d",
            "created_by_ref": "identity--0581a0ae-0be3-473a-a9fe-eb784433f1fa",
            "created": "2025-09-03T16:02:49.426532Z",
            "modified": "2025-09-03T16:02:49.426532Z",
            "relationship_type": "uses",
            "source_ref": "malware--d6bba528-b310-49d2-bc39-0e95e11d0a3a",
            "target_ref": "attack-pattern--d770181c-ec4b-4d46-861e-7a3253f1b884"
        },
        {
            "type": "relationship",
            "spec_version": "2.1",
            "id": "relationship--68f4cd76-070a-4245-9e5b-7cd15e3ecec2",
            "created_by_ref": "identity--0581a0ae-0be3-473a-a9fe-eb784433f1fa",
            "created": "2025-09-03T16:02:49.426851Z",
            "modified": "2025-09-03T16:02:49.426851Z",
            "relationship_type": "uses",
            "source_ref": "malware--d6bba528-b310-49d2-bc39-0e95e11d0a3a",
            "target_ref": "attack-pattern--b6660b88-6f3c-44cc-9a6f-ab5a8392a0bd"
        },
        {
            "type": "relationship",
            "spec_version": "2.1",
            "id": "relationship--dd3c8a7d-6be6-4d9e-87db-36a5c22c74eb",
            "created_by_ref": "identity--0581a0ae-0be3-473a-a9fe-eb784433f1fa",
            "created": "2025-09-03T16:02:49.427132Z",
            "modified": "2025-09-03T16:02:49.427132Z",
            "relationship_type": "uses",
            "source_ref": "malware--d6bba528-b310-49d2-bc39-0e95e11d0a3a",
            "target_ref": "attack-pattern--2077f92b-a864-4aa7-a53d-c326ff66f115"
        },
        {
            "type": "relationship",
            "spec_version": "2.1",
            "id": "relationship--b6ca4af0-03ef-44c9-b797-29ae92a78dde",
            "created_by_ref": "identity--0581a0ae-0be3-473a-a9fe-eb784433f1fa",
            "created": "2025-09-03T16:02:49.427842Z",
            "modified": "2025-09-03T16:02:49.427842Z",
            "relationship_type": "uses",
            "source_ref": "malware--d6bba528-b310-49d2-bc39-0e95e11d0a3a",
            "target_ref": "attack-pattern--863f75b6-ea4a-4042-ae1c-91fe3cdc0b23"
        },
        {
            "type": "relationship",
            "spec_version": "2.1",
            "id": "relationship--39dd8599-a0e1-4eef-a17c-d93dc2f2aaf9",
            "created_by_ref": "identity--0581a0ae-0be3-473a-a9fe-eb784433f1fa",
            "created": "2025-09-03T16:02:49.429234Z",
            "modified": "2025-09-03T16:02:49.429234Z",
            "relationship_type": "uses",
            "source_ref": "malware--d6bba528-b310-49d2-bc39-0e95e11d0a3a",
            "target_ref": "attack-pattern--b96bf485-0431-45d5-8e9a-fccf58687d43"
        },
        {
            "type": "relationship",
            "spec_version": "2.1",
            "id": "relationship--498de893-d28f-4d70-81b9-150451822be9",
            "created_by_ref": "identity--0581a0ae-0be3-473a-a9fe-eb784433f1fa",
            "created": "2025-09-03T16:02:49.429941Z",
            "modified": "2025-09-03T16:02:49.429941Z",
            "relationship_type": "uses",
            "source_ref": "malware--d6bba528-b310-49d2-bc39-0e95e11d0a3a",
            "target_ref": "attack-pattern--91b75f4f-2413-4ebd-bd0a-5b6c582f75fa"
        },
        {
            "type": "relationship",
            "spec_version": "2.1",
            "id": "relationship--f2c55f84-1814-44ed-a260-e95deb55fc7f",
            "created_by_ref": "identity--0581a0ae-0be3-473a-a9fe-eb784433f1fa",
            "created": "2025-09-03T16:02:49.4304Z",
            "modified": "2025-09-03T16:02:49.4304Z",
            "relationship_type": "uses",
            "source_ref": "malware--d6bba528-b310-49d2-bc39-0e95e11d0a3a",
            "target_ref": "attack-pattern--5972dad2-46b7-479f-a7a6-b33869705a61"
        },
        {
            "type": "relationship",
            "spec_version": "2.1",
            "id": "relationship--c8b06d41-b99e-4f5e-9e17-8acf561a3a5e",
            "created_by_ref": "identity--0581a0ae-0be3-473a-a9fe-eb784433f1fa",
            "created": "2025-09-03T16:02:49.431015Z",
            "modified": "2025-09-03T16:02:49.431015Z",
            "relationship_type": "uses",
            "source_ref": "malware--d6bba528-b310-49d2-bc39-0e95e11d0a3a",
            "target_ref": "attack-pattern--8f8c7403-a552-4418-b9a0-88aa997ea801"
        },
        {
            "type": "relationship",
            "spec_version": "2.1",
            "id": "relationship--9de7acaa-310c-45c4-bec0-c2aa9abda6a6",
            "created_by_ref": "identity--0581a0ae-0be3-473a-a9fe-eb784433f1fa",
            "created": "2025-09-03T16:02:49.431348Z",
            "modified": "2025-09-03T16:02:49.431348Z",
            "relationship_type": "uses",
            "source_ref": "malware--d6bba528-b310-49d2-bc39-0e95e11d0a3a",
            "target_ref": "attack-pattern--173212d5-ac35-4839-b2eb-74038a88f433"
        },
        {
            "type": "relationship",
            "spec_version": "2.1",
            "id": "relationship--52d14e41-e544-4d67-80a0-1ec4371d1f7f",
            "created_by_ref": "identity--0581a0ae-0be3-473a-a9fe-eb784433f1fa",
            "created": "2025-09-03T16:02:49.432063Z",
            "modified": "2025-09-03T16:02:49.432063Z",
            "relationship_type": "indicates",
            "source_ref": "indicator--34d4da07-0522-4e8a-99e9-960a0b332111",
            "target_ref": "malware--d6bba528-b310-49d2-bc39-0e95e11d0a3a"
        },
        {
            "type": "relationship",
            "spec_version": "2.1",
            "id": "relationship--931d8bd1-0e43-4032-9294-fb2ef4273921",
            "created_by_ref": "identity--0581a0ae-0be3-473a-a9fe-eb784433f1fa",
            "created": "2025-09-03T16:02:49.432541Z",
            "modified": "2025-09-03T16:02:49.432541Z",
            "relationship_type": "indicates",
            "source_ref": "indicator--a3406e06-71ce-4cac-b448-093cf9067923",
            "target_ref": "malware--d6bba528-b310-49d2-bc39-0e95e11d0a3a"
        },
        {
            "type": "relationship",
            "spec_version": "2.1",
            "id": "relationship--f59fc45e-4c73-447c-84f8-4463797ca753",
            "created_by_ref": "identity--0581a0ae-0be3-473a-a9fe-eb784433f1fa",
            "created": "2025-09-03T16:02:49.43298Z",
            "modified": "2025-09-03T16:02:49.43298Z",
            "relationship_type": "indicates",
            "source_ref": "indicator--283ce6c3-0eb9-4277-8b1a-a8de401eef30",
            "target_ref": "malware--d6bba528-b310-49d2-bc39-0e95e11d0a3a"
        },
        {
            "type": "relationship",
            "spec_version": "2.1",
            "id": "relationship--e12d651b-30cb-400e-af27-ba4c226fddcd",
            "created_by_ref": "identity--0581a0ae-0be3-473a-a9fe-eb784433f1fa",
            "created": "2025-09-03T16:02:49.433246Z",
            "modified": "2025-09-03T16:02:49.433246Z",
            "relationship_type": "indicates",
            "source_ref": "indicator--b73e98d7-bee5-4404-8eb1-4b876bab4588",
            "target_ref": "malware--d6bba528-b310-49d2-bc39-0e95e11d0a3a"
        },
        {
            "type": "relationship",
            "spec_version": "2.1",
            "id": "relationship--235ca930-73fa-407f-a4d0-99e82c1edf98",
            "created_by_ref": "identity--0581a0ae-0be3-473a-a9fe-eb784433f1fa",
            "created": "2025-09-03T16:02:49.433524Z",
            "modified": "2025-09-03T16:02:49.433524Z",
            "relationship_type": "indicates",
            "source_ref": "indicator--bf86823d-fd0f-4c75-9ac4-f4177af58ea8",
            "target_ref": "malware--d6bba528-b310-49d2-bc39-0e95e11d0a3a"
        },
        {
            "type": "relationship",
            "spec_version": "2.1",
            "id": "relationship--f0da96e3-dd98-4005-90ce-7abd8ed662ad",
            "created_by_ref": "identity--0581a0ae-0be3-473a-a9fe-eb784433f1fa",
            "created": "2025-09-03T16:02:49.433903Z",
            "modified": "2025-09-03T16:02:49.433903Z",
            "relationship_type": "indicates",
            "source_ref": "indicator--48f74225-c480-4404-b8c0-118de8de833c",
            "target_ref": "malware--d6bba528-b310-49d2-bc39-0e95e11d0a3a"
        },
        {
            "type": "relationship",
            "spec_version": "2.1",
            "id": "relationship--0757912f-39e4-4042-bd02-f08b4b6fd921",
            "created_by_ref": "identity--0581a0ae-0be3-473a-a9fe-eb784433f1fa",
            "created": "2025-09-03T16:02:49.434428Z",
            "modified": "2025-09-03T16:02:49.434428Z",
            "relationship_type": "indicates",
            "source_ref": "indicator--5acc1604-8dc7-4596-aeb5-f750ff08e7d8",
            "target_ref": "malware--d6bba528-b310-49d2-bc39-0e95e11d0a3a"
        },
        {
            "type": "relationship",
            "spec_version": "2.1",
            "id": "relationship--056dad9a-d12d-4a81-ab77-61c56f567786",
            "created_by_ref": "identity--0581a0ae-0be3-473a-a9fe-eb784433f1fa",
            "created": "2025-09-03T16:02:49.435065Z",
            "modified": "2025-09-03T16:02:49.435065Z",
            "relationship_type": "indicates",
            "source_ref": "indicator--3241cd79-ce7b-4846-bc5d-d76743b08873",
            "target_ref": "malware--d6bba528-b310-49d2-bc39-0e95e11d0a3a"
        },
        {
            "type": "relationship",
            "spec_version": "2.1",
            "id": "relationship--6acf3b13-6864-4992-aa9a-67bbc3608a71",
            "created_by_ref": "identity--0581a0ae-0be3-473a-a9fe-eb784433f1fa",
            "created": "2025-09-03T16:02:49.435411Z",
            "modified": "2025-09-03T16:02:49.435411Z",
            "relationship_type": "indicates",
            "source_ref": "indicator--2bb3af37-3765-4530-84aa-db9924b5944c",
            "target_ref": "malware--d6bba528-b310-49d2-bc39-0e95e11d0a3a"
        },
        {
            "type": "relationship",
            "spec_version": "2.1",
            "id": "relationship--53e895e3-6a88-46d6-93b4-5c189e16e8cf",
            "created_by_ref": "identity--0581a0ae-0be3-473a-a9fe-eb784433f1fa",
            "created": "2025-09-03T16:02:49.435959Z",
            "modified": "2025-09-03T16:02:49.435959Z",
            "relationship_type": "indicates",
            "source_ref": "indicator--ee5ef927-1169-40e5-9008-8d8e6da9d96e",
            "target_ref": "malware--d6bba528-b310-49d2-bc39-0e95e11d0a3a"
        },
        {
            "type": "relationship",
            "spec_version": "2.1",
            "id": "relationship--fa116b33-c54d-4dd1-a1f0-ea5bd4069972",
            "created_by_ref": "identity--0581a0ae-0be3-473a-a9fe-eb784433f1fa",
            "created": "2025-09-03T16:02:49.436626Z",
            "modified": "2025-09-03T16:02:49.436626Z",
            "relationship_type": "indicates",
            "source_ref": "indicator--725e9ab8-506f-4a7f-a10d-c61dfa495e69",
            "target_ref": "malware--d6bba528-b310-49d2-bc39-0e95e11d0a3a"
        },
        {
            "type": "relationship",
            "spec_version": "2.1",
            "id": "relationship--d9cbb5d6-a6fa-4e11-a3c5-1ca77b2e9460",
            "created_by_ref": "identity--0581a0ae-0be3-473a-a9fe-eb784433f1fa",
            "created": "2025-09-03T16:02:49.437177Z",
            "modified": "2025-09-03T16:02:49.437177Z",
            "relationship_type": "indicates",
            "source_ref": "indicator--ab13d847-e37f-48f4-ad23-6737b56b7f2b",
            "target_ref": "malware--d6bba528-b310-49d2-bc39-0e95e11d0a3a"
        },
        {
            "type": "relationship",
            "spec_version": "2.1",
            "id": "relationship--6d89933e-e40f-4eb7-acf4-308511889877",
            "created_by_ref": "identity--0581a0ae-0be3-473a-a9fe-eb784433f1fa",
            "created": "2025-09-03T16:02:49.437614Z",
            "modified": "2025-09-03T16:02:49.437614Z",
            "relationship_type": "indicates",
            "source_ref": "indicator--de3d0f52-1835-4c58-903e-4838008264d6",
            "target_ref": "malware--d6bba528-b310-49d2-bc39-0e95e11d0a3a"
        },
        {
            "type": "relationship",
            "spec_version": "2.1",
            "id": "relationship--b121fa2a-b21c-42e3-bba5-c0ac7bc3dfd2",
            "created_by_ref": "identity--0581a0ae-0be3-473a-a9fe-eb784433f1fa",
            "created": "2025-09-03T16:02:49.438451Z",
            "modified": "2025-09-03T16:02:49.438451Z",
            "relationship_type": "indicates",
            "source_ref": "indicator--91dce08a-738b-490b-b6e7-0b3681b71144",
            "target_ref": "malware--d6bba528-b310-49d2-bc39-0e95e11d0a3a"
        },
        {
            "type": "relationship",
            "spec_version": "2.1",
            "id": "relationship--1631130c-d7ac-4f2a-90c8-e5c7363680ee",
            "created_by_ref": "identity--0581a0ae-0be3-473a-a9fe-eb784433f1fa",
            "created": "2025-09-03T16:02:49.438788Z",
            "modified": "2025-09-03T16:02:49.438788Z",
            "relationship_type": "indicates",
            "source_ref": "indicator--66ce15bb-8dd3-4824-8033-f4d7b375640a",
            "target_ref": "malware--d6bba528-b310-49d2-bc39-0e95e11d0a3a"
        },
        {
            "type": "relationship",
            "spec_version": "2.1",
            "id": "relationship--6e200c22-7fc3-47de-afaa-aa69e227f835",
            "created_by_ref": "identity--0581a0ae-0be3-473a-a9fe-eb784433f1fa",
            "created": "2025-09-03T16:02:49.439103Z",
            "modified": "2025-09-03T16:02:49.439103Z",
            "relationship_type": "indicates",
            "source_ref": "indicator--80e1e57f-42ba-4a47-b719-cd11cf9a1f18",
            "target_ref": "malware--d6bba528-b310-49d2-bc39-0e95e11d0a3a"
        },
        {
            "type": "relationship",
            "spec_version": "2.1",
            "id": "relationship--2e42bba9-0196-4b5d-a2ba-d4c1833a9727",
            "created_by_ref": "identity--0581a0ae-0be3-473a-a9fe-eb784433f1fa",
            "created": "2025-09-03T16:02:49.439659Z",
            "modified": "2025-09-03T16:02:49.439659Z",
            "relationship_type": "indicates",
            "source_ref": "indicator--5f257659-687a-4da4-8779-f0d50dd80149",
            "target_ref": "malware--d6bba528-b310-49d2-bc39-0e95e11d0a3a"
        },
        {
            "type": "relationship",
            "spec_version": "2.1",
            "id": "relationship--77187a9e-8c92-4559-82c4-53071743fd35",
            "created_by_ref": "identity--0581a0ae-0be3-473a-a9fe-eb784433f1fa",
            "created": "2025-09-03T16:02:49.439964Z",
            "modified": "2025-09-03T16:02:49.439964Z",
            "relationship_type": "indicates",
            "source_ref": "indicator--0fa6a97b-431f-4755-8aca-ce5065ac97ef",
            "target_ref": "malware--d6bba528-b310-49d2-bc39-0e95e11d0a3a"
        },
        {
            "type": "relationship",
            "spec_version": "2.1",
            "id": "relationship--abc39db0-918d-428e-b858-ada5a8fa61f6",
            "created_by_ref": "identity--0581a0ae-0be3-473a-a9fe-eb784433f1fa",
            "created": "2025-09-03T16:02:49.440475Z",
            "modified": "2025-09-03T16:02:49.440475Z",
            "relationship_type": "indicates",
            "source_ref": "indicator--82e339c5-ecf7-41a4-a307-b8360d0c3906",
            "target_ref": "malware--d6bba528-b310-49d2-bc39-0e95e11d0a3a"
        },
        {
            "type": "relationship",
            "spec_version": "2.1",
            "id": "relationship--688eff81-4273-4229-8673-cd5b737a225d",
            "created_by_ref": "identity--0581a0ae-0be3-473a-a9fe-eb784433f1fa",
            "created": "2025-09-03T16:02:49.440951Z",
            "modified": "2025-09-03T16:02:49.440951Z",
            "relationship_type": "indicates",
            "source_ref": "indicator--923fe82f-3cd7-4847-8c3a-ffb924b15c60",
            "target_ref": "malware--d6bba528-b310-49d2-bc39-0e95e11d0a3a"
        },
        {
            "type": "relationship",
            "spec_version": "2.1",
            "id": "relationship--0e10a3da-804f-4b64-a180-c0b5a76ecb69",
            "created_by_ref": "identity--0581a0ae-0be3-473a-a9fe-eb784433f1fa",
            "created": "2025-09-03T16:02:49.441504Z",
            "modified": "2025-09-03T16:02:49.441504Z",
            "relationship_type": "indicates",
            "source_ref": "indicator--1dbf6839-dd3c-4ea6-a23e-72ff3e3d673a",
            "target_ref": "malware--d6bba528-b310-49d2-bc39-0e95e11d0a3a"
        },
        {
            "type": "relationship",
            "spec_version": "2.1",
            "id": "relationship--71558675-99fa-4d28-92f0-471cfd484a79",
            "created_by_ref": "identity--0581a0ae-0be3-473a-a9fe-eb784433f1fa",
            "created": "2025-09-03T16:02:49.442046Z",
            "modified": "2025-09-03T16:02:49.442046Z",
            "relationship_type": "indicates",
            "source_ref": "indicator--e28df472-b0fa-44aa-a6c8-01750564d8c1",
            "target_ref": "malware--d6bba528-b310-49d2-bc39-0e95e11d0a3a"
        },
        {
            "type": "relationship",
            "spec_version": "2.1",
            "id": "relationship--2b56d439-5834-417f-86a1-c7e16a502cd8",
            "created_by_ref": "identity--0581a0ae-0be3-473a-a9fe-eb784433f1fa",
            "created": "2025-09-03T16:02:49.442377Z",
            "modified": "2025-09-03T16:02:49.442377Z",
            "relationship_type": "indicates",
            "source_ref": "indicator--7b183e8b-314f-4e0e-b979-d037b1683cfa",
            "target_ref": "malware--d6bba528-b310-49d2-bc39-0e95e11d0a3a"
        },
        {
            "type": "relationship",
            "spec_version": "2.1",
            "id": "relationship--4f2d7384-634b-45cf-a7ad-23ac51e41527",
            "created_by_ref": "identity--0581a0ae-0be3-473a-a9fe-eb784433f1fa",
            "created": "2025-09-03T16:02:49.442928Z",
            "modified": "2025-09-03T16:02:49.442928Z",
            "relationship_type": "indicates",
            "source_ref": "indicator--60a8c520-87a6-4f85-a03e-d13649cc00b9",
            "target_ref": "malware--d6bba528-b310-49d2-bc39-0e95e11d0a3a"
        },
        {
            "type": "relationship",
            "spec_version": "2.1",
            "id": "relationship--4f36c8c6-fb08-4a3f-84de-d0b798bb7069",
            "created_by_ref": "identity--0581a0ae-0be3-473a-a9fe-eb784433f1fa",
            "created": "2025-09-03T16:02:49.443253Z",
            "modified": "2025-09-03T16:02:49.443253Z",
            "relationship_type": "indicates",
            "source_ref": "indicator--48d064d2-2a75-4b09-a6d9-34a02d2323ae",
            "target_ref": "malware--d6bba528-b310-49d2-bc39-0e95e11d0a3a"
        },
        {
            "type": "relationship",
            "spec_version": "2.1",
            "id": "relationship--46aeaf83-9bb7-492b-b6b3-f60c3adf02fd",
            "created_by_ref": "identity--0581a0ae-0be3-473a-a9fe-eb784433f1fa",
            "created": "2025-09-03T16:02:49.443929Z",
            "modified": "2025-09-03T16:02:49.443929Z",
            "relationship_type": "indicates",
            "source_ref": "indicator--d8fe363e-e12f-4cd8-a397-c4155b2a2903",
            "target_ref": "malware--d6bba528-b310-49d2-bc39-0e95e11d0a3a"
        },
        {
            "type": "relationship",
            "spec_version": "2.1",
            "id": "relationship--49e09dc0-d44f-4ae9-af82-c4e378bbdeed",
            "created_by_ref": "identity--0581a0ae-0be3-473a-a9fe-eb784433f1fa",
            "created": "2025-09-03T16:02:49.444555Z",
            "modified": "2025-09-03T16:02:49.444555Z",
            "relationship_type": "derived-from",
            "source_ref": "indicator--d8fe363e-e12f-4cd8-a397-c4155b2a2903",
            "target_ref": "indicator--1dbf6839-dd3c-4ea6-a23e-72ff3e3d673a"
        },
        {
            "type": "relationship",
            "spec_version": "2.1",
            "id": "relationship--c231268b-9f03-4fd0-af57-f7396efff87a",
            "created_by_ref": "identity--0581a0ae-0be3-473a-a9fe-eb784433f1fa",
            "created": "2025-09-03T16:02:49.444886Z",
            "modified": "2025-09-03T16:02:49.444886Z",
            "relationship_type": "derived-from",
            "source_ref": "indicator--d8fe363e-e12f-4cd8-a397-c4155b2a2903",
            "target_ref": "indicator--60a8c520-87a6-4f85-a03e-d13649cc00b9"
        },
        {
            "type": "relationship",
            "spec_version": "2.1",
            "id": "relationship--791fd0d9-4fc8-4090-a304-a292b31a51bb",
            "created_by_ref": "identity--0581a0ae-0be3-473a-a9fe-eb784433f1fa",
            "created": "2025-09-03T16:02:49.445253Z",
            "modified": "2025-09-03T16:02:49.445253Z",
            "relationship_type": "indicates",
            "source_ref": "indicator--8c20ca67-7a6b-4463-a3db-30a5fa979760",
            "target_ref": "malware--d6bba528-b310-49d2-bc39-0e95e11d0a3a"
        },
        {
            "type": "relationship",
            "spec_version": "2.1",
            "id": "relationship--ca79b7d4-e12a-4e10-ace5-5b60226ba43e",
            "created_by_ref": "identity--0581a0ae-0be3-473a-a9fe-eb784433f1fa",
            "created": "2025-09-03T16:02:49.445542Z",
            "modified": "2025-09-03T16:02:49.445542Z",
            "relationship_type": "derived-from",
            "source_ref": "indicator--8c20ca67-7a6b-4463-a3db-30a5fa979760",
            "target_ref": "indicator--1dbf6839-dd3c-4ea6-a23e-72ff3e3d673a"
        },
        {
            "type": "relationship",
            "spec_version": "2.1",
            "id": "relationship--53f8b6dd-87e1-467d-b409-e7408fe42834",
            "created_by_ref": "identity--0581a0ae-0be3-473a-a9fe-eb784433f1fa",
            "created": "2025-09-03T16:02:49.445857Z",
            "modified": "2025-09-03T16:02:49.445857Z",
            "relationship_type": "derived-from",
            "source_ref": "indicator--8c20ca67-7a6b-4463-a3db-30a5fa979760",
            "target_ref": "indicator--60a8c520-87a6-4f85-a03e-d13649cc00b9"
        },
        {
            "type": "relationship",
            "spec_version": "2.1",
            "id": "relationship--f6128fc6-4f7c-46b4-abff-2ee708f1077c",
            "created_by_ref": "identity--0581a0ae-0be3-473a-a9fe-eb784433f1fa",
            "created": "2025-09-03T16:02:49.44625Z",
            "modified": "2025-09-03T16:02:49.44625Z",
            "relationship_type": "indicates",
            "source_ref": "indicator--f8e3c02f-7900-4c89-8f76-1d6865303f89",
            "target_ref": "malware--d6bba528-b310-49d2-bc39-0e95e11d0a3a"
        },
        {
            "type": "relationship",
            "spec_version": "2.1",
            "id": "relationship--91481b53-3c88-48f0-847a-dc2019262286",
            "created_by_ref": "identity--0581a0ae-0be3-473a-a9fe-eb784433f1fa",
            "created": "2025-09-03T16:02:49.446573Z",
            "modified": "2025-09-03T16:02:49.446573Z",
            "relationship_type": "derived-from",
            "source_ref": "indicator--f8e3c02f-7900-4c89-8f76-1d6865303f89",
            "target_ref": "indicator--1dbf6839-dd3c-4ea6-a23e-72ff3e3d673a"
        },
        {
            "type": "relationship",
            "spec_version": "2.1",
            "id": "relationship--95a4fcea-66cd-4fa2-b795-a8cc51a0e6af",
            "created_by_ref": "identity--0581a0ae-0be3-473a-a9fe-eb784433f1fa",
            "created": "2025-09-03T16:02:49.447024Z",
            "modified": "2025-09-03T16:02:49.447024Z",
            "relationship_type": "indicates",
            "source_ref": "indicator--117843eb-9f5b-4533-b47c-aa29fd4c6954",
            "target_ref": "malware--d6bba528-b310-49d2-bc39-0e95e11d0a3a"
        },
        {
            "type": "relationship",
            "spec_version": "2.1",
            "id": "relationship--a5afa2cc-b4aa-469a-aa75-2f69e60d0d58",
            "created_by_ref": "identity--0581a0ae-0be3-473a-a9fe-eb784433f1fa",
            "created": "2025-09-03T16:02:49.447329Z",
            "modified": "2025-09-03T16:02:49.447329Z",
            "relationship_type": "derived-from",
            "source_ref": "indicator--117843eb-9f5b-4533-b47c-aa29fd4c6954",
            "target_ref": "indicator--1dbf6839-dd3c-4ea6-a23e-72ff3e3d673a"
        },
        {
            "type": "relationship",
            "spec_version": "2.1",
            "id": "relationship--6fed7d0f-52ab-4327-99ac-98505aba25cd",
            "created_by_ref": "identity--0581a0ae-0be3-473a-a9fe-eb784433f1fa",
            "created": "2025-09-03T16:02:49.448037Z",
            "modified": "2025-09-03T16:02:49.448037Z",
            "relationship_type": "indicates",
            "source_ref": "indicator--7314879c-9085-4111-99fc-2d41961d4a4f",
            "target_ref": "malware--d6bba528-b310-49d2-bc39-0e95e11d0a3a"
        },
        {
            "type": "relationship",
            "spec_version": "2.1",
            "id": "relationship--0f6a1e0e-272b-45bc-be10-1cf4ae006a75",
            "created_by_ref": "identity--0581a0ae-0be3-473a-a9fe-eb784433f1fa",
            "created": "2025-09-03T16:02:49.44866Z",
            "modified": "2025-09-03T16:02:49.44866Z",
            "relationship_type": "derived-from",
            "source_ref": "indicator--7314879c-9085-4111-99fc-2d41961d4a4f",
            "target_ref": "indicator--1dbf6839-dd3c-4ea6-a23e-72ff3e3d673a"
        },
        {
            "type": "relationship",
            "spec_version": "2.1",
            "id": "relationship--8ac4389b-93f7-4d31-ae4d-aafc8ec63bfa",
            "created_by_ref": "identity--0581a0ae-0be3-473a-a9fe-eb784433f1fa",
            "created": "2025-09-03T16:02:49.449282Z",
            "modified": "2025-09-03T16:02:49.449282Z",
            "relationship_type": "indicates",
            "source_ref": "indicator--5218bc5c-e59b-4fa3-be17-ffa88ac4d177",
            "target_ref": "malware--d6bba528-b310-49d2-bc39-0e95e11d0a3a"
        },
        {
            "type": "relationship",
            "spec_version": "2.1",
            "id": "relationship--a06adc43-338e-4782-9699-a2ec2702ffdf",
            "created_by_ref": "identity--0581a0ae-0be3-473a-a9fe-eb784433f1fa",
            "created": "2025-09-03T16:02:49.449841Z",
            "modified": "2025-09-03T16:02:49.449841Z",
            "relationship_type": "derived-from",
            "source_ref": "indicator--5218bc5c-e59b-4fa3-be17-ffa88ac4d177",
            "target_ref": "indicator--60a8c520-87a6-4f85-a03e-d13649cc00b9"
        },
        {
            "type": "report",
            "spec_version": "2.1",
            "id": "report--5388e229-1874-4ec6-8e3e-1ee805a05bc8",
            "created_by_ref": "identity--0581a0ae-0be3-473a-a9fe-eb784433f1fa",
            "created": "2025-09-03T16:02:49.450512Z",
            "modified": "2025-09-03T16:02:49.450512Z",
            "name": "Analisi Malware: Smooth Operator",
            "description": "This report contains technical analysis and indicators associated with malware. smooth operator.",
            "report_types": [
                "malware-analysis"
            ],
            "published": "2025-09-03T16:02:49.450497Z",
            "object_refs": [
                "identity--0581a0ae-0be3-473a-a9fe-eb784433f1fa",
                "url--3ca77848-3c86-5177-b9c7-262d440d813f",
                "url--3ce4a838-3d16-5dae-a0e0-e04cd86b5de5",
                "url--c0df7321-5a23-5833-a830-d26ac9be888a",
                "url--9bb50a9b-3b49-5ec4-bd4b-f6218f0a3291",
                "url--dbe40f12-c563-5543-859e-b7e68f643b2e",
                "url--7fdbe136-4ff2-52f3-a597-f76d4438fdfd",
                "url--67d95451-80b8-5473-bb76-d2120307ba1b",
                "url--e6657594-2903-51f3-87db-e23c6b55deef",
                "url--3ea4b73b-cfa2-58dc-9dc7-1cff719316d6",
                "url--8096d021-fbde-5c5c-bdde-579339fed002",
                "url--d4c0c66e-acd2-52b3-b82b-eeb29120e0c6",
                "url--62529b3b-96ed-53cf-938e-ae44eca99914",
                "url--6d15f2ac-747b-5b8c-8325-f9994aaf02ee",
                "url--230a9427-bc2b-56b1-96a0-5d6274096e11",
                "url--4523eebd-2121-542b-9aef-3fdaf7184a3f",
                "url--a91f7562-d8f2-5f71-b267-2be460045132",
                "indicator--34d4da07-0522-4e8a-99e9-960a0b332111",
                "indicator--a3406e06-71ce-4cac-b448-093cf9067923",
                "indicator--283ce6c3-0eb9-4277-8b1a-a8de401eef30",
                "indicator--b73e98d7-bee5-4404-8eb1-4b876bab4588",
                "indicator--bf86823d-fd0f-4c75-9ac4-f4177af58ea8",
                "indicator--48f74225-c480-4404-b8c0-118de8de833c",
                "indicator--5acc1604-8dc7-4596-aeb5-f750ff08e7d8",
                "indicator--3241cd79-ce7b-4846-bc5d-d76743b08873",
                "indicator--2bb3af37-3765-4530-84aa-db9924b5944c",
                "indicator--ee5ef927-1169-40e5-9008-8d8e6da9d96e",
                "indicator--725e9ab8-506f-4a7f-a10d-c61dfa495e69",
                "indicator--ab13d847-e37f-48f4-ad23-6737b56b7f2b",
                "indicator--de3d0f52-1835-4c58-903e-4838008264d6",
                "indicator--91dce08a-738b-490b-b6e7-0b3681b71144",
                "indicator--66ce15bb-8dd3-4824-8033-f4d7b375640a",
                "indicator--80e1e57f-42ba-4a47-b719-cd11cf9a1f18",
                "indicator--5f257659-687a-4da4-8779-f0d50dd80149",
                "indicator--0fa6a97b-431f-4755-8aca-ce5065ac97ef",
                "indicator--82e339c5-ecf7-41a4-a307-b8360d0c3906",
                "indicator--923fe82f-3cd7-4847-8c3a-ffb924b15c60",
                "indicator--1dbf6839-dd3c-4ea6-a23e-72ff3e3d673a",
                "indicator--e28df472-b0fa-44aa-a6c8-01750564d8c1",
                "indicator--7b183e8b-314f-4e0e-b979-d037b1683cfa",
                "indicator--60a8c520-87a6-4f85-a03e-d13649cc00b9",
                "indicator--48d064d2-2a75-4b09-a6d9-34a02d2323ae",
                "relationship--6d72f72c-c509-47dc-bb01-bb589fbd9faf",
                "relationship--1f006d62-4bad-4373-bdc2-2e6a18f90eb9",
                "relationship--85e0b11e-430f-4a07-be97-66f9a82822a8",
                "relationship--50e38c24-292b-44c6-b145-cf9897ce8c22",
                "relationship--a3a5bee6-6c10-4357-9bd6-96ba3aea7bc5",
                "relationship--6bf29b02-f240-430a-a40f-338d7e01fd14",
                "relationship--822694a8-bb0d-43ba-846a-7e1a806f5cfe",
                "relationship--8c2c1575-3baf-4abd-8c97-bde61bf06974",
                "relationship--78b06ad9-4547-42ec-8ae3-d6c6aeebb764",
                "relationship--7ce83242-74e3-4151-9232-1a472510d823",
                "relationship--d7f19581-973c-49e6-a308-54105415b5e2",
                "relationship--0b17ad7b-0621-4061-955d-cd908b987d17",
                "relationship--ccdbb85b-d569-4d16-865e-62458e2c131a",
                "relationship--57288741-53fa-47b8-86cc-4323a9ed5066",
                "relationship--505bab61-df92-4ae5-a44f-5be10b18e3ea",
                "relationship--9df15e70-d11e-4eba-be0d-14a735718662",
                "relationship--01e0dfec-87c0-475c-a08c-445831a26455",
                "relationship--473cc04c-f229-4a45-ab48-aa63547dea59",
                "relationship--878b89e5-130e-4365-91ad-db326ba88707",
                "relationship--3710aef7-16aa-48d8-8a3c-0b9d03f2fbdc",
                "relationship--148547f5-69a2-4bd0-b9e7-faf0db3422d7",
                "relationship--c8cd1bb8-e6d8-4507-9daf-1f9c2a33aebc",
                "relationship--b59f6c6c-a4a8-42ea-950b-499c1d3adf80",
                "relationship--ba17838b-27ac-4ddd-83ea-b7840396a445",
                "relationship--7c09ccb5-e7e9-4f7e-856b-14a38b0b4ef7",
                "malware--d6bba528-b310-49d2-bc39-0e95e11d0a3a",
                "malware--73ae42a4-0657-4684-8cf9-7072f1b0167f",
                "identity--f728f373-1940-4acf-aa55-3e64f77092c7",
                "identity--4a4837d4-0963-4274-af89-6eb311ca6054",
                "indicator--d8fe363e-e12f-4cd8-a397-c4155b2a2903",
                "indicator--8c20ca67-7a6b-4463-a3db-30a5fa979760",
                "indicator--f8e3c02f-7900-4c89-8f76-1d6865303f89",
                "indicator--117843eb-9f5b-4533-b47c-aa29fd4c6954",
                "indicator--7314879c-9085-4111-99fc-2d41961d4a4f",
                "indicator--5218bc5c-e59b-4fa3-be17-ffa88ac4d177",
                "attack-pattern--d770181c-ec4b-4d46-861e-7a3253f1b884",
                "attack-pattern--b6660b88-6f3c-44cc-9a6f-ab5a8392a0bd",
                "attack-pattern--2077f92b-a864-4aa7-a53d-c326ff66f115",
                "attack-pattern--863f75b6-ea4a-4042-ae1c-91fe3cdc0b23",
                "attack-pattern--b96bf485-0431-45d5-8e9a-fccf58687d43",
                "attack-pattern--91b75f4f-2413-4ebd-bd0a-5b6c582f75fa",
                "attack-pattern--5972dad2-46b7-479f-a7a6-b33869705a61",
                "attack-pattern--8f8c7403-a552-4418-b9a0-88aa997ea801",
                "attack-pattern--173212d5-ac35-4839-b2eb-74038a88f433",
                "relationship--6f17d42d-8c99-421c-85a2-e32d803c665d",
                "relationship--68f4cd76-070a-4245-9e5b-7cd15e3ecec2",
                "relationship--dd3c8a7d-6be6-4d9e-87db-36a5c22c74eb",
                "relationship--b6ca4af0-03ef-44c9-b797-29ae92a78dde",
                "relationship--39dd8599-a0e1-4eef-a17c-d93dc2f2aaf9",
                "relationship--498de893-d28f-4d70-81b9-150451822be9",
                "relationship--f2c55f84-1814-44ed-a260-e95deb55fc7f",
                "relationship--c8b06d41-b99e-4f5e-9e17-8acf561a3a5e",
                "relationship--9de7acaa-310c-45c4-bec0-c2aa9abda6a6",
                "relationship--52d14e41-e544-4d67-80a0-1ec4371d1f7f",
                "relationship--931d8bd1-0e43-4032-9294-fb2ef4273921",
                "relationship--f59fc45e-4c73-447c-84f8-4463797ca753",
                "relationship--e12d651b-30cb-400e-af27-ba4c226fddcd",
                "relationship--235ca930-73fa-407f-a4d0-99e82c1edf98",
                "relationship--f0da96e3-dd98-4005-90ce-7abd8ed662ad",
                "relationship--0757912f-39e4-4042-bd02-f08b4b6fd921",
                "relationship--056dad9a-d12d-4a81-ab77-61c56f567786",
                "relationship--6acf3b13-6864-4992-aa9a-67bbc3608a71",
                "relationship--53e895e3-6a88-46d6-93b4-5c189e16e8cf",
                "relationship--fa116b33-c54d-4dd1-a1f0-ea5bd4069972",
                "relationship--d9cbb5d6-a6fa-4e11-a3c5-1ca77b2e9460",
                "relationship--6d89933e-e40f-4eb7-acf4-308511889877",
                "relationship--b121fa2a-b21c-42e3-bba5-c0ac7bc3dfd2",
                "relationship--1631130c-d7ac-4f2a-90c8-e5c7363680ee",
                "relationship--6e200c22-7fc3-47de-afaa-aa69e227f835",
                "relationship--2e42bba9-0196-4b5d-a2ba-d4c1833a9727",
                "relationship--77187a9e-8c92-4559-82c4-53071743fd35",
                "relationship--abc39db0-918d-428e-b858-ada5a8fa61f6",
                "relationship--688eff81-4273-4229-8673-cd5b737a225d",
                "relationship--0e10a3da-804f-4b64-a180-c0b5a76ecb69",
                "relationship--71558675-99fa-4d28-92f0-471cfd484a79",
                "relationship--2b56d439-5834-417f-86a1-c7e16a502cd8",
                "relationship--4f2d7384-634b-45cf-a7ad-23ac51e41527",
                "relationship--4f36c8c6-fb08-4a3f-84de-d0b798bb7069",
                "relationship--46aeaf83-9bb7-492b-b6b3-f60c3adf02fd",
                "relationship--49e09dc0-d44f-4ae9-af82-c4e378bbdeed",
                "relationship--c231268b-9f03-4fd0-af57-f7396efff87a",
                "relationship--791fd0d9-4fc8-4090-a304-a292b31a51bb",
                "relationship--ca79b7d4-e12a-4e10-ace5-5b60226ba43e",
                "relationship--53f8b6dd-87e1-467d-b409-e7408fe42834",
                "relationship--f6128fc6-4f7c-46b4-abff-2ee708f1077c",
                "relationship--91481b53-3c88-48f0-847a-dc2019262286",
                "relationship--95a4fcea-66cd-4fa2-b795-a8cc51a0e6af",
                "relationship--a5afa2cc-b4aa-469a-aa75-2f69e60d0d58",
                "relationship--6fed7d0f-52ab-4327-99ac-98505aba25cd",
                "relationship--0f6a1e0e-272b-45bc-be10-1cf4ae006a75",
                "relationship--8ac4389b-93f7-4d31-ae4d-aafc8ec63bfa",
                "relationship--a06adc43-338e-4782-9699-a2ec2702ffdf"
            ],
            "object_marking_refs": [
                "marking-definition--613f2e26-407d-48c7-9eca-b8e91df99dc9"
            ]
        }
    ]
}